rs_fec_conv-0.4.5.dist-info/METADATA
rs_fec_conv-0.4.5.dist-info/WHEEL
rs_fec_conv/fec_conv.py
rs_fec_conv/__init__.py
rs_fec_conv/__version__.py
rs_fec_conv/rs_fec_conv.cpython-37m-x86_64-linux-gnu.so
rs_fec_conv-0.4.5.dist-info/RECORD
