Metadata-Version: 2.1
Name: rs_fec_conv
Version: 0.4.5
Summary: Convolutional Encoder and Viterbi Decoder built with Rust bindings for integration with Python
Author: Benjamin Roepken <broepken57@hotmail.com>
Author-Email: Benjamin Roepken <broepken57@hotmail.com>
